{
  "gitSyncId": "668baad67b0e48213cd7eeb6_3284b64e-d9f2-4b51-85a2-951548d49857",
  "id": "View Licenses Copy5_getPricesByProductIds",
  "pluginId": "restapi-plugin",
  "pluginType": "API",
  "unpublishedAction": {
    "actionConfiguration": {
      "autoGeneratedHeaders": [],
      "bodyFormData": [],
      "encodeParamsToggle": true,
      "formData": {
        "apiContentType": "none"
      },
      "headers": [],
      "httpMethod": "GET",
      "paginationType": "NONE",
      "path": "/v1/prices/search",
      "queryParameters": [
        {
          "key": "query",
          "value": "{{SubscriptionUtils.createSearchQuery()}}"
        },
        {
          "key": "limit",
          "value": "100"
        }
      ],
      "timeoutInMillisecond": 10000
    },
    "confirmBeforeExecute": false,
    "datasource": {
      "id": "Stripe Datasource",
      "isAutoGenerated": false,
      "name": "Stripe Datasource",
      "pluginId": "restapi-plugin"
    },
    "dynamicBindingPathList": [
      {
        "key": "path"
      },
      {
        "key": "queryParameters[0].value"
      }
    ],
    "executeOnLoad": false,
    "name": "getPricesByProductIds",
    "pageId": "View Licenses Copy5",
    "userSetOnLoad": true
  }
}