{
  "gitSyncId": "668baad67b0e48213cd7eeb6_991a3647-65c5-411d-96c8-8eb3651cd98b",
  "id": "View Licenses Copy9_revokeLicenseById",
  "pluginId": "restapi-plugin",
  "pluginType": "API",
  "unpublishedAction": {
    "actionConfiguration": {
      "autoGeneratedHeaders": [
        {
          "key": "content-type",
          "value": "application/json"
        }
      ],
      "body": "",
      "bodyFormData": [],
      "encodeParamsToggle": true,
      "formData": {
        "apiContentType": "none"
      },
      "headers": [],
      "httpMethod": "DELETE",
      "paginationType": "NONE",
      "path": "/api/v1/enterprise/license/{{this.params.licenseId}}",
      "pluginSpecifiedTemplates": [
        {
          "value": true
        }
      ],
      "queryParameters": [],
      "timeoutInMillisecond": 10000
    },
    "confirmBeforeExecute": false,
    "datasource": {
      "id": "CS_Datasource",
      "isAutoGenerated": false,
      "name": "CS_Datasource",
      "pluginId": "restapi-plugin"
    },
    "dynamicBindingPathList": [
      {
        "key": "path"
      }
    ],
    "executeOnLoad": false,
    "name": "revokeLicenseById",
    "pageId": "View Licenses Copy9",
    "userSetOnLoad": false
  }
}