{
  "gitSyncId": "668baad67b0e48213cd7eeb6_9a1d74ab-09f4-4bfd-91b8-f0acb380f64b",
  "id": "View Licenses Copy Copy_getLicenseById",
  "pluginId": "restapi-plugin",
  "pluginType": "API",
  "unpublishedAction": {
    "actionConfiguration": {
      "autoGeneratedHeaders": [],
      "bodyFormData": [],
      "encodeParamsToggle": true,
      "formData": {
        "apiContentType": "none"
      },
      "headers": [],
      "httpMethod": "GET",
      "paginationType": "NONE",
      "path": "/api/v1/enterprise/license/{{LicenseTable.triggeredRow?.licenseId}}",
      "pluginSpecifiedTemplates": [
        {
          "value": true
        }
      ],
      "queryParameters": [],
      "timeoutInMillisecond": 10000
    },
    "confirmBeforeExecute": false,
    "datasource": {
      "id": "CS_Datasource",
      "isAutoGenerated": false,
      "name": "CS_Datasource",
      "pluginId": "restapi-plugin"
    },
    "dynamicBindingPathList": [
      {
        "key": "path"
      }
    ],
    "executeOnLoad": false,
    "name": "getLicenseById",
    "pageId": "View Licenses Copy Copy",
    "userSetOnLoad": true
  }
}