{
  "gitSyncId": "668baad67b0e48213cd7eeb6_8615f63c-72d5-4bb4-bd83-60bcf600a30c",
  "id": "View Licenses Copy6_Utils.getEncodedUri",
  "pluginId": "js-plugin",
  "pluginType": "JS",
  "unpublishedAction": {
    "actionConfiguration": {
      "encodeParamsToggle": true,
      "isAsync": false,
      "jsArguments": [
        {
          "name": "uri"
        }
      ],
      "paginationType": "NONE",
      "timeoutInMillisecond": 10000
    },
    "collectionId": "View Licenses Copy6_Utils",
    "confirmBeforeExecute": false,
    "datasource": {
      "isAutoGenerated": false,
      "name": "UNUSED_DATASOURCE",
      "pluginId": "js-plugin"
    },
    "dynamicBindingPathList": [
      {
        "key": "body"
      }
    ],
    "executeOnLoad": false,
    "fullyQualifiedName": "Utils.getEncodedUri",
    "name": "getEncodedUri",
    "pageId": "View Licenses Copy6",
    "userSetOnLoad": false
  }
}