{
  "gitSyncId": "668baad67b0e48213cd7eeb6_35c7d8a0-863d-46bc-8dac-982254428736",
  "id": "View Licenses Copy2_Actions.createPriceItem",
  "pluginId": "js-plugin",
  "pluginType": "JS",
  "unpublishedAction": {
    "actionConfiguration": {
      "encodeParamsToggle": true,
      "isAsync": true,
      "jsArguments": [],
      "paginationType": "NONE",
      "timeoutInMillisecond": 10000
    },
    "collectionId": "View Licenses Copy2_Actions",
    "confirmBeforeExecute": false,
    "datasource": {
      "isAutoGenerated": false,
      "name": "UNUSED_DATASOURCE",
      "pluginId": "js-plugin"
    },
    "dynamicBindingPathList": [
      {
        "key": "body"
      }
    ],
    "executeOnLoad": false,
    "fullyQualifiedName": "Actions.createPriceItem",
    "name": "createPriceItem",
    "pageId": "View Licenses Copy2",
    "userSetOnLoad": false
  }
}